anvil_rl/__init__.py
anvil_rl/agents/__init__.py
anvil_rl/agents/base_agent.py
anvil_rl/agents/ddpg.py
anvil_rl/agents/dqn.py
anvil_rl/buffers/__init__.py
anvil_rl/buffers/base_buffer.py
anvil_rl/buffers/her_buffer.py
anvil_rl/buffers/replay_buffer.py
anvil_rl/buffers/rollout_buffer.py
anvil_rl/callbacks/__init__.py
anvil_rl/callbacks/base_callback.py
anvil_rl/callbacks/checkpoint_callback.py
anvil_rl/common/enumerations.py
anvil_rl/common/type_aliases.py
anvil_rl/common/utils.py
anvil_rl/explorers/__init__.py
anvil_rl/explorers/base_explorer.py
anvil_rl/explorers/gaussian_explorer.py
anvil_rl/models/__init__.py
anvil_rl/models/actor_critics.py
anvil_rl/models/encoders.py
anvil_rl/models/heads.py
anvil_rl/models/torsos.py
anvil_rl/models/utils.py
anvil_rl/signal_processing/__init__.py
anvil_rl/signal_processing/sample_estimators.py
anvil_rl/updaters/__init__.py
anvil_rl/updaters/actors.py
anvil_rl/updaters/critics.py
anvil_rl-0.1.0.dist-info/WHEEL
anvil_rl-0.1.0.dist-info/METADATA
anvil_rl-0.1.0.dist-info/RECORD
